pythlete/__init__.py
pythlete/general.py
pythlete/pitstop.py
pythlete/safetycar.py
pythlete/strategy.py
pythlete/telemetry.py
pythlete-1.0.0.dist-info/METADATA
pythlete-1.0.0.dist-info/WHEEL
pythlete-1.0.0.dist-info/top_level.txt
pythlete-1.0.0.dist-info/RECORD
